flask_apium/__init__.py
flask_apium/make_celery.py
Flask_Apium-0.0.1.dist-info/LICENSE
Flask_Apium-0.0.1.dist-info/METADATA
Flask_Apium-0.0.1.dist-info/WHEEL
Flask_Apium-0.0.1.dist-info/top_level.txt
Flask_Apium-0.0.1.dist-info/RECORD
