Metadata-Version: 2.1
Name: Flask-Apium
Version: 0.0.1
License-File: LICENSE
Requires-Dist: flask
Requires-Dist: celery[sqlalchemy]
